<gallery>
	<column>
		<pic>n01.webp</pic>
		<pic>n02.webp</pic>
		<pic>n03.webp</pic>
		<pic>n04.webp</pic>
		<pic>n05.webp</pic>
		<pic>n06.webp</pic>
	</column>
	<column>
		<pic>n11.webp</pic>
		<pic>n12.webp</pic>
		<pic>n13.webp</pic>
		<pic>n14.webp</pic>
		<pic>n15.webp</pic>
		<pic>n16.webp</pic>


	</column>
	<column>
		<pic>n21.webp</pic>
		<pic>n22.webp</pic>
		<pic>n23.webp</pic>
		<pic>n24.webp</pic>
		<pic>n25.webp</pic>
		<pic>n26.webp</pic>
	</column>

</gallery>